seeq/addons/email/common/__init__.py
seeq/addons/email/common/_copy.py
seeq/addons/email/common/_installer.py
seeq/addons/email/common/_utils.py
seeq/addons/email/common/ui_components/__init__.py
seeq/addons/email/common/ui_components/_app_unsubscriber.py
seeq/addons/email/common/ui_components/_footer.py
seeq/addons/email/common/ui_components/_jobs.py
seeq/addons/email/common/ui_components/_snackbar.py
seeq/addons/email/common/ui_components/_templating.py
seeq/addons/email/common/ui_components/vue_templates/_app_unsubscriber.vue
seeq/addons/email/common/ui_components/vue_templates/_footer.vue
seeq/addons/email/common/ui_components/vue_templates/_jobs.vue
seeq/addons/email/common/ui_components/vue_templates/_snackbar.vue
seeq/addons/email/common/ui_components/vue_templates/_templating.vue
seeq/addons/email/condition_monitor/__init__.py
seeq/addons/email/condition_monitor/_capsule_handler.py
seeq/addons/email/condition_monitor/_condition_monitor_scheduler.py
seeq/addons/email/condition_monitor/_email_builder.py
seeq/addons/email/condition_monitor/_installer.py
seeq/addons/email/condition_monitor/_notifier.py
seeq/addons/email/condition_monitor/_unsubscriber.py
seeq/addons/email/condition_monitor/_version.py
seeq/addons/email/condition_monitor/deploy_notebooks/Condition Monitor Scheduler.ipynb
seeq/addons/email/condition_monitor/deploy_notebooks/Email Condition Monitor Installer.ipynb
seeq/addons/email/condition_monitor/deploy_notebooks/Notifier.ipynb
seeq/addons/email/condition_monitor/deploy_notebooks/Unsubscriber.ipynb
seeq/addons/email/condition_monitor/ui_components/__init__.py
seeq/addons/email/condition_monitor/ui_components/_app_scheduler.py
seeq/addons/email/condition_monitor/ui_components/_condition.py
seeq/addons/email/condition_monitor/ui_components/_scheduling.py
seeq/addons/email/condition_monitor/ui_components/_tabs.py
seeq/addons/email/condition_monitor/ui_components/vue_templates/_app_scheduler.vue
seeq_email_condition_monitor-0.3.3.dist-info/LICENSE
seeq_email_condition_monitor-0.3.3.dist-info/METADATA
seeq_email_condition_monitor-0.3.3.dist-info/WHEEL
seeq_email_condition_monitor-0.3.3.dist-info/top_level.txt
seeq_email_condition_monitor-0.3.3.dist-info/RECORD
