Metadata-Version: 2.1
Name: seeq-email-condition-monitor
Version: 0.3.3
Summary: Data Lab Notebook-based Email Condition Monitor Scheduling tool
Home-page: 
Author: Alberto Rivas
Author-email: alberto.rivas@seeq.com
License: Apache License 2.0
Platform: Linux
Platform: Windows
Classifier: Programming Language :: Python :: 3.8
Classifier: License :: OSI Approved :: Apache Software License
Classifier: Operating System :: OS Independent
Requires-Python: >=3.8
License-File: LICENSE
Requires-Dist: jsonschema (>=4.16.0)
Requires-Dist: beautifulsoup4 (>=4.9.3)
Requires-Dist: pytz (>=2022.4)
